cloud_helper/__init__.py
cloud_helper/aws_helper/__init__.py
cloud_helper/aws_helper/connections.py
cloud_helper-1.0.1.dist-info/LICENSE
cloud_helper-1.0.1.dist-info/METADATA
cloud_helper-1.0.1.dist-info/WHEEL
cloud_helper-1.0.1.dist-info/top_level.txt
cloud_helper-1.0.1.dist-info/RECORD
