Metadata-Version: 2.1
Name: cloud-helper
Version: 1.0.1
Summary: A convenient Helper library for various cloud services
Home-page: https://github.com/papunmohanty/cloud-helper
Author: Papun Mohanty
Author-email: reachtopmohanty@gmail.com
License: MIT
Platform: UNKNOWN
Classifier: License :: OSI Approved :: MIT License
Classifier: Programming Language :: Python :: 3
Classifier: Programming Language :: Python :: 3.8
Requires-Dist: boto3
